bertserini_on_telegram/__init__.py
bertserini_on_telegram/data/__init__.py
bertserini_on_telegram/data/datamodules.py
bertserini_on_telegram/models/__init__.py
bertserini_on_telegram/models/modules.py
bertserini_on_telegram/utils/__init__.py
bertserini_on_telegram/utils/base.py
bertserini_on_telegram/utils/constants.py
bertserini_on_telegram/utils/io.py
bertserini_on_telegram/utils/pyserini.py
bertserini_on_telegram/utils/translate.py
bertserini_on_telegram/utils/utils_squad.py
bertserini_on_telegram-1.2.dist-info/LICENSE
bertserini_on_telegram-1.2.dist-info/METADATA
bertserini_on_telegram-1.2.dist-info/WHEEL
bertserini_on_telegram-1.2.dist-info/top_level.txt
bertserini_on_telegram-1.2.dist-info/RECORD
