Metadata-Version: 2.1
Name: bertserini-on-telegram
Version: 1.2
Summary: A library, based on PyTorch, that implements bertserini code.
Home-page: https://github.com/Nico995/Bertserini-on-Telegram
Author: Nicola Occelli
Author-email: nicola.occelli@studenti.polito.it
License: UNKNOWN
Platform: UNKNOWN
Classifier: Programming Language :: Python :: 3
Classifier: License :: OSI Approved :: MIT License
Classifier: Operating System :: OS Independent
Requires-Python: >=3.7
License-File: LICENSE
Requires-Dist: torch
Requires-Dist: torchvision
Requires-Dist: pytorch-lightning
Requires-Dist: transformers
Requires-Dist: pyserini
Requires-Dist: telegram
Requires-Dist: datasets
Requires-Dist: faiss-gpu
Requires-Dist: fasttext
Requires-Dist: iso639
Requires-Dist: jsonargparse
